aries_askar/__init__.py
aries_askar/aries_askar.dll
aries_askar/bindings/__init__.py
aries_askar/bindings/handle.py
aries_askar/bindings/lib.py
aries_askar/crypto_box.py
aries_askar/ecdh.py
aries_askar/error.py
aries_askar/kdf.py
aries_askar/key.py
aries_askar/store.py
aries_askar/types.py
aries_askar-0.5.0.dist-info/METADATA
aries_askar-0.5.0.dist-info/WHEEL
aries_askar-0.5.0.dist-info/RECORD
