Metadata-Version: 2.4
Name: aries_askar
Version: 0.5.0
Summary: Python wrapper for the Aries Askar cryptographic library
License: Apache-2.0
Keywords: cryptography,aries,verifiable credentials
Author: OpenWallet Foundation Askar Contributors
Requires-Python: >=3.10,<4.0
Classifier: License :: OSI Approved :: Apache Software License
Classifier: Programming Language :: Python :: 3
Classifier: Programming Language :: Python :: 3.10
Classifier: Programming Language :: Python :: 3.11
Classifier: Programming Language :: Python :: 3.12
Classifier: Programming Language :: Python :: 3.13
Classifier: Programming Language :: Python :: 3.14
Project-URL: Homepage, https://github.com/openwallet-foundation/askar
Project-URL: Repository, https://github.com/openwallet-foundation/askar
